lemontest/__init__.py
lemontest/djangorunner.py
lemontest/djangox.py
lemontest-0.4.6.dist-info/LICENSE
lemontest-0.4.6.dist-info/METADATA
lemontest-0.4.6.dist-info/WHEEL
lemontest-0.4.6.dist-info/entry_points.txt
lemontest-0.4.6.dist-info/top_level.txt
lemontest-0.4.6.dist-info/RECORD
